mvneuro/__init__.py
mvneuro/base.py
mvneuro/multiviewica.py
mvneuro-0.0.0.dist-info/LICENSE
mvneuro-0.0.0.dist-info/METADATA
mvneuro-0.0.0.dist-info/WHEEL
mvneuro-0.0.0.dist-info/top_level.txt
mvneuro-0.0.0.dist-info/RECORD
