Metadata-Version: 2.1
Name: mvneuro
Version: 0.0.0
Summary: A multiview package for neuroscience
Home-page: UNKNOWN
License: UNKNOWN
Platform: UNKNOWN
Requires-Python: >=3
Requires-Dist: numpy
Requires-Dist: sklearn
Requires-Dist: fastsrm
Requires-Dist: multiviewica
